setup.py
rogrepos/__init__.py
rogrepos/rogrepos.py
rogrepos.egg-info/PKG-INFO
rogrepos.egg-info/SOURCES.txt
rogrepos.egg-info/dependency_links.txt
rogrepos.egg-info/entry_points.txt
rogrepos.egg-info/requires.txt
rogrepos.egg-info/top_level.txt
rogrepos.egg-info/zip-safe