Metadata-Version: 1.1
Name: rogrepos
Version: 0.1.1
Summary: Rogrepos removes outdated GitHub repositories
Home-page: http://github.com/lqez/rogrepos
Author: Park Hyunwoo
Author-email: ez.amiryo@gmail.com
License: UNKNOWN
Platform: UNKNOWN
Classifier: Topic :: Terminals
Classifier: Topic :: Utilities
Classifier: Environment :: Console
Classifier: Development Status :: 4 - Beta
Classifier: Intended Audience :: Developers
Classifier: Intended Audience :: System Administrators
Classifier: Programming Language :: Python
Classifier: License :: OSI Approved :: MIT License
